brudercropper/__init__.py
brudercropper/__main__.py
brudercropper/crop.py
brudercropper-0.1.95.dist-info/LICENSE
brudercropper-0.1.95.dist-info/METADATA
brudercropper-0.1.95.dist-info/WHEEL
brudercropper-0.1.95.dist-info/entry_points.txt
brudercropper-0.1.95.dist-info/top_level.txt
brudercropper-0.1.95.dist-info/RECORD
