Metadata-Version: 2.1
Name: brudercropper
Version: 0.1.95
Summary: Croppt Zeug auf 62mm für Bruderlabeldrucker
Home-page: UNKNOWN
Author: Niggo
License: UNKNOWN
Platform: UNKNOWN
Classifier: Programming Language :: Python :: 3
Classifier: Operating System :: OS Independent
Requires-Python: >=3.5
License-File: LICENSE
Requires-Dist: imutils
Requires-Dist: numpy
Requires-Dist: opencv-python
Requires-Dist: Pillow (>=8)
Requires-Dist: pytesseract (==0.3.7)
Requires-Dist: python-barcode
